yaml2instance/__init__.py
yaml2instance/main.py
yaml2instance-0.2.0.dist-info/LICENSE
yaml2instance-0.2.0.dist-info/WHEEL
yaml2instance-0.2.0.dist-info/METADATA
yaml2instance-0.2.0.dist-info/RECORD
